html2notion/__init__.py
html2notion/main.py
html2notion/translate/__init__.py
html2notion/translate/aa.py
html2notion/translate/batch_import.py
html2notion/translate/cos_uploader.py
html2notion/translate/html2json.py
html2notion/translate/html2json_base.py
html2notion/translate/html2json_clipper.py
html2notion/translate/html2json_default.py
html2notion/translate/html2json_markdown.py
html2notion/translate/html2json_yinxiang.py
html2notion/translate/import_stats.py
html2notion/translate/notion_export.py
html2notion/translate/notion_import.py
html2notion/utils/__init__.py
html2notion/utils/convert.py
html2notion/utils/diffutils.py
html2notion/utils/load_config.py
html2notion/utils/log.py
html2notion/utils/timeutil.py
html2notion/utils/url_process.py
html2notion-0.2.0.dist-info/LICENSE
html2notion-0.2.0.dist-info/METADATA
html2notion-0.2.0.dist-info/WHEEL
html2notion-0.2.0.dist-info/entry_points.txt
html2notion-0.2.0.dist-info/top_level.txt
html2notion-0.2.0.dist-info/RECORD
