Metadata-Version: 2.1
Name: html2notion
Version: 0.2.0
Summary: This tool can accurately convert HTML to Notion notes and is also useful for exporting Evernote notes to Notion.
Home-page: https://github.com/selfboot/html2notion
Author: selfboot
Author-email: xuezaigds@gmail.com
Classifier: Programming Language :: Python :: 3
Classifier: License :: OSI Approved :: MIT License
Classifier: Operating System :: OS Independent
License-File: LICENSE
